ivneuro/__init__.py
ivneuro/continuous.py
ivneuro/delta_coherence.py
ivneuro/delta_coherence_core.py
ivneuro/delta_power_spectral.py
ivneuro/delta_power_spectral_core.py
ivneuro/events.py
ivneuro/generate_signal.py
ivneuro/spectograms.py
ivneuro/spectograms_core.py
ivneuro/tracking.py
ivneuro/utils.py
ivneuro/nex/NexData.py
ivneuro/nex/__init__.py
ivneuro/nex/nexfile.py
ivneuro/nex/pull_nex_data.py
ivneuro-0.1.3.dist-info/LICENSE
ivneuro-0.1.3.dist-info/METADATA
ivneuro-0.1.3.dist-info/WHEEL
ivneuro-0.1.3.dist-info/top_level.txt
ivneuro-0.1.3.dist-info/RECORD
