Metadata-Version: 2.1
Name: ivneuro
Version: 0.1.3
Summary: Tools for processing and analyzing neurophysiological signals recorded in-vivo.
Home-page: https://github.com/casey-e/ivneuro
Author: Eric Casey
Author-email: e.toccalino@gmail.com
License: MIT
Project-URL: Homepage, https://github.com/casey-e/ivneuro
Requires-Python: >=3.11.3
License-File: LICENSE
Requires-Dist: numpy (>=1.24.1)
Requires-Dist: pandas (>=2.0.1)
Requires-Dist: matplotlib (>=3.6.2)
Requires-Dist: scipy (>=1.10)
